pkgsearch/__init__.py
pkgsearch/psearch.py
pkgsearch-0.1.0.dist-info/METADATA
pkgsearch-0.1.0.dist-info/WHEEL
pkgsearch-0.1.0.dist-info/entry_points.txt
pkgsearch-0.1.0.dist-info/top_level.txt
pkgsearch-0.1.0.dist-info/RECORD
