Metadata-Version: 2.1
Name: pkgsearch
Version: 0.1.0
Summary: A package to search for versions of packages from various repositorie and list versions
Home-page: https://github.com/5bhuv4n35h/pkgsearch
Author: kanigten
Author-email: 10207922+5bhuv4n35h@users.noreply.github.com
Classifier: Programming Language :: Python :: 3
Classifier: License :: OSI Approved :: MIT License
Classifier: Operating System :: OS Independent
Requires-Python: >=3.6
Requires-Dist: requests
Requires-Dist: packaging
Requires-Dist: pyperclip
